hack4u/__init__.py
hack4u/courses.py
hack4u/utils.py
pipe4u-0.1.0.dist-info/METADATA
pipe4u-0.1.0.dist-info/WHEEL
pipe4u-0.1.0.dist-info/top_level.txt
pipe4u-0.1.0.dist-info/RECORD
