Metadata-Version: 2.1
Name: pipe4u
Version: 0.1.0
Summary: Una biblioteca para consultar cursos de hack4u.
Home-page: https://hack4u.io
Author: Luis Felipe Castaño Villada
